spectacularme/__init__.py
spectacularme/spectacularme.py
spectacularme-0.0.4.dist-info/METADATA
spectacularme-0.0.4.dist-info/WHEEL
spectacularme-0.0.4.dist-info/top_level.txt
spectacularme-0.0.4.dist-info/RECORD
